{
    "createdTime": "2025-11-15T09:47:10Z",
    "referenceTime": "2025-11-15T09:30:00Z",
    "geometry": {
      "type": "Point",
      "coordinates": [18.823101, 68.35379]
    },
    "timeSeries": [
      {
        "time": "2025-11-15T10:00:00Z",
        "intervalParametersStartTime": "2025-11-15T09:00:00Z",
        "data": {
          "air_temperature": -3.2,
          "wind_from_direction": 87,
          "wind_speed": 3.2,
          "wind_speed_of_gust": 6.2,
          "relative_humidity": 89,
          "air_pressure_at_mean_sea_level": 990.8,
          "visibility_in_air": 0.9,
          "thunderstorm_probability": 0,
          "probability_of_frozen_precipitation": 0.01,
          "cloud_area_fraction": 8,
          "low_type_cloud_area_fraction": 8,
          "medium_type_cloud_area_fraction": 8,
          "high_type_cloud_area_fraction": 3,
          "cloud_base_altitude": 784,
          "cloud_top_altitude": 3617,
          "mtpr": 0,
          "precipitation_amount_mean": 0.2,
          "precipitation_amount_min": 0.3,
          "precipitation_amount_max": 0.5,
          "precipitation_amount_median": 0,
          "probability_of_precipitation": 40,
          "precipitation_frozen_part": 1,
          "predominant_precipitation_type_at_surface": 5,
          "symbol_code": 7
        }
      },
      {
        "time": "2025-11-15T11:00:00Z",
        "intervalParametersStartTime": "2025-11-15T10:00:00Z",
        "data": {
          "air_temperature": -3.2,
          "wind_from_direction": 104,
          "wind_speed": 1.8,
          "wind_speed_of_gust": 6.1,
          "relative_humidity": 91,
          "air_pressure_at_mean_sea_level": 989.5,
          "visibility_in_air": 1.4,
          "thunderstorm_probability": 0.01,
          "probability_of_frozen_precipitation": 0.01,
          "cloud_area_fraction": 8,
          "low_type_cloud_area_fraction": 8,
          "medium_type_cloud_area_fraction": 8,
          "high_type_cloud_area_fraction": 3,
          "cloud_base_altitude": 1401,
          "cloud_top_altitude": 2725,
          "mtpr": 0,
          "precipitation_amount_mean": 0.2,
          "precipitation_amount_min": 0.3,
          "precipitation_amount_max": 0.8,
          "precipitation_amount_median": 0,
          "probability_of_precipitation": 40,
          "precipitation_frozen_part": 1,
          "predominant_precipitation_type_at_surface": 5,
          "symbol_code": 6
        }
      },
      {
        "time": "2025-11-15T12:00:00Z",
        "intervalParametersStartTime": "2025-11-15T11:00:00Z",
        "data": {
          "air_temperature": -2.8,
          "wind_from_direction": 34,
          "wind_speed": 0.1,
          "wind_speed_of_gust": 3.4,
          "relative_humidity": 91,
          "air_pressure_at_mean_sea_level": 988.7,
          "visibility_in_air": 1.5,
          "thunderstorm_probability": 0.01,
          "probability_of_frozen_precipitation": 0.01,
          "cloud_area_fraction": 8,
          "low_type_cloud_area_fraction": 8,
          "medium_type_cloud_area_fraction": 8,
          "high_type_cloud_area_fraction": 4,
          "cloud_base_altitude": 2526,
          "cloud_top_altitude": 3871,
          "mtpr": 0,
          "precipitation_amount_mean": 0.5,
          "precipitation_amount_min": 0.3,
          "precipitation_amount_max": 0.6,
          "precipitation_amount_median": 0.4,
          "probability_of_precipitation": 100,
          "precipitation_frozen_part": 1,
          "predominant_precipitation_type_at_surface": 5,
          "symbol_code": 25
        }
      },
      {
        "time": "2025-11-15T13:00:00Z",
        "intervalParametersStartTime": "2025-11-15T12:00:00Z",
        "data": {
          "air_temperature": -2.7,
          "wind_from_direction": 62,
          "wind_speed": 1,
          "wind_speed_of_gust": 2,
          "relative_humidity": 93,
          "air_pressure_at_mean_sea_level": 988.6,
          "visibility_in_air": 1.3,
          "thunderstorm_probability": 0.01,
          "probability_of_frozen_precipitation": 0.01,
          "cloud_area_fraction": 8,
          "low_type_cloud_area_fraction": 8,
          "medium_type_cloud_area_fraction": 8,
          "high_type_cloud_area_fraction": 6,
          "cloud_base_altitude": 1672,
          "cloud_top_altitude": 4975,
          "mtpr": 0,
          "precipitation_amount_mean": 0.7,
          "precipitation_amount_min": 0.4,
          "precipitation_amount_max": 0.9,
          "precipitation_amount_median": 0.6,
          "probability_of_precipitation": 100,
          "precipitation_frozen_part": 1,
          "predominant_precipitation_type_at_surface": 5,
          "symbol_code": 26
        }
      },
      {
        "time": "2025-11-15T14:00:00Z",
        "intervalParametersStartTime": "2025-11-15T13:00:00Z",
        "data": {
          "air_temperature": -2.7,
          "wind_from_direction": 98,
          "wind_speed": 0.3,
          "wind_speed_of_gust": 2.1,
          "relative_humidity": 93,
          "air_pressure_at_mean_sea_level": 988.5,
          "visibility_in_air": 1.4,
          "thunderstorm_probability": 0.01,
          "probability_of_frozen_precipitation": 0.01,
          "cloud_area_fraction": 8,
          "low_type_cloud_area_fraction": 8,
          "medium_type_cloud_area_fraction": 8,
          "high_type_cloud_area_fraction": 8,
          "cloud_base_altitude": 5931,
          "cloud_top_altitude": 7431,
          "mtpr": 0,
          "precipitation_amount_mean": 0.6,
          "precipitation_amount_min": 0.5,
          "precipitation_amount_max": 0.8,
          "precipitation_amount_median": 0.6,
          "probability_of_precipitation": 100,
          "precipitation_frozen_part": 1,
          "predominant_precipitation_type_at_surface": 5,
          "symbol_code": 26
        }
      },
      {
        "time": "2025-11-15T15:00:00Z",
        "intervalParametersStartTime": "2025-11-15T14:00:00Z",
        "data": {
          "air_temperature": -2.8,
          "wind_from_direction": 62,
          "wind_speed": 0.9,
          "wind_speed_of_gust": 1.7,
          "relative_humidity": 94,
          "air_pressure_at_mean_sea_level": 988.6,
          "visibility_in_air": 1,
          "thunderstorm_probability": 0.01,
          "probability_of_frozen_precipitation": 0.01,
          "cloud_area_fraction": 8,
          "low_type_cloud_area_fraction": 8,
          "medium_type_cloud_area_fraction": 8,
          "high_type_cloud_area_fraction": 8,
          "cloud_base_altitude": 569,
          "cloud_top_altitude": 6643,
          "mtpr": 0,
          "precipitation_amount_mean": 0.6,
          "precipitation_amount_min": 0.4,
          "precipitation_amount_max": 0.7,
          "precipitation_amount_median": 0.6,
          "probability_of_precipitation": 100,
          "precipitation_frozen_part": 1,
          "predominant_precipitation_type_at_surface": 5,
          "symbol_code": 26
        }
      },
      {
        "time": "2025-11-15T16:00:00Z",
        "intervalParametersStartTime": "2025-11-15T15:00:00Z",
        "data": {
          "air_temperature": -2.3,
          "wind_from_direction": 339,
          "wind_speed": 1.9,
          "wind_speed_of_gust": 3.7,
          "relative_humidity": 89,
          "air_pressure_at_mean_sea_level": 989,
          "visibility_in_air": 2.2,
          "thunderstorm_probability": 0,
          "probability_of_frozen_precipitation": 0.01,
          "cloud_area_fraction": 8,
          "low_type_cloud_area_fraction": 8,
          "medium_type_cloud_area_fraction": 7,
          "high_type_cloud_area_fraction": 5,
          "cloud_base_altitude": 9999,
          "cloud_top_altitude": 9999,
          "mtpr": 0,
          "precipitation_amount_mean": 0.4,
          "precipitation_amount_min": 0.3,
          "precipitation_amount_max": 0.5,
          "precipitation_amount_median": 0.4,
          "probability_of_precipitation": 97,
          "precipitation_frozen_part": 1,
          "predominant_precipitation_type_at_surface": 5,
          "symbol_code": 25
        }
      },
      {
        "time": "2025-11-15T17:00:00Z",
        "intervalParametersStartTime": "2025-11-15T16:00:00Z",
        "data": {
          "air_temperature": -2.2,
          "wind_from_direction": 313,
          "wind_speed": 2.7,
          "wind_speed_of_gust": 5.1,
          "relative_humidity": 72,
          "air_pressure_at_mean_sea_level": 989.5,
          "visibility_in_air": 4.8,
          "thunderstorm_probability": 0,
          "probability_of_frozen_precipitation": 0,
          "cloud_area_fraction": 8,
          "low_type_cloud_area_fraction": 7,
          "medium_type_cloud_area_fraction": 6,
          "high_type_cloud_area_fraction": 3,
          "cloud_base_altitude": 9999,
          "cloud_top_altitude": 9999,
          "mtpr": 0,
          "precipitation_amount_mean": 0.2,
          "precipitation_amount_min": 0.1,
          "precipitation_amount_max": 0.3,
          "precipitation_amount_median": 0.2,
          "probability_of_precipitation": 83,
          "precipitation_frozen_part": 1,
          "predominant_precipitation_type_at_surface": 5,
          "symbol_code": 25
        }
      },
      {
        "time": "2025-11-15T18:00:00Z",
        "intervalParametersStartTime": "2025-11-15T17:00:00Z",
        "data": {
          "air_temperature": -2.6,
          "wind_from_direction": 314,
          "wind_speed": 4.1,
          "wind_speed_of_gust": 7.9,
          "relative_humidity": 71,
          "air_pressure_at_mean_sea_level": 990.4,
          "visibility_in_air": 41,
          "thunderstorm_probability": 0,
          "probability_of_frozen_precipitation": 0,
          "cloud_area_fraction": 7,
          "low_type_cloud_area_fraction": 5,
          "medium_type_cloud_area_fraction": 4,
          "high_type_cloud_area_fraction": 0,
          "cloud_base_altitude": 9999,
          "cloud_top_altitude": 9999,
          "mtpr": 0,
          "precipitation_amount_mean": 0.1,
          "precipitation_amount_min": 0.1,
          "precipitation_amount_max": 0.3,
          "precipitation_amount_median": 0,
          "probability_of_precipitation": 40,
          "precipitation_frozen_part": 1,
          "predominant_precipitation_type_at_surface": 5,
          "symbol_code": 4
        }
      },
      {
        "time": "2025-11-15T19:00:00Z",
        "intervalParametersStartTime": "2025-11-15T18:00:00Z",
        "data": {
          "air_temperature": -3.2,
          "wind_from_direction": 315,
          "wind_speed": 4,
          "wind_speed_of_gust": 8.2,
          "relative_humidity": 75,
          "air_pressure_at_mean_sea_level": 991.2,
          "visibility_in_air": 36.1,
          "thunderstorm_probability": 0,
          "probability_of_frozen_precipitation": 0,
          "cloud_area_fraction": 5,
          "low_type_cloud_area_fraction": 4,
          "medium_type_cloud_area_fraction": 1,
          "high_type_cloud_area_fraction": 0,
          "cloud_base_altitude": 9999,
          "cloud_top_altitude": 9999,
          "mtpr": 0,
          "precipitation_amount_mean": 0,
          "precipitation_amount_min": 0.1,
          "precipitation_amount_max": 0.2,
          "precipitation_amount_median": 0,
          "probability_of_precipitation": 13,
          "precipitation_frozen_part": 1,
          "predominant_precipitation_type_at_surface": 5,
          "symbol_code": 3
        }
      },
      {
        "time": "2025-11-15T20:00:00Z",
        "intervalParametersStartTime": "2025-11-15T19:00:00Z",
        "data": {
          "air_temperature": -3.7,
          "wind_from_direction": 307,
          "wind_speed": 2.6,
          "wind_speed_of_gust": 7.6,
          "relative_humidity": 79,
          "air_pressure_at_mean_sea_level": 991.7,
          "visibility_in_air": 75,
          "thunderstorm_probability": 0,
          "probability_of_frozen_precipitation": 0,
          "cloud_area_fraction": 4,
          "low_type_cloud_area_fraction": 4,
          "medium_type_cloud_area_fraction": 0,
          "high_type_cloud_area_fraction": 0,
          "cloud_base_altitude": 9999,
          "cloud_top_altitude": 9999,
          "mtpr": 0,
          "precipitation_amount_mean": 0,
          "precipitation_amount_min": 0,
          "precipitation_amount_max": 0,
          "precipitation_amount_median": 0,
          "probability_of_precipitation": 0,
          "precipitation_frozen_part": -9,
          "predominant_precipitation_type_at_surface": 0,
          "symbol_code": 3
        }
      },
      {
        "time": "2025-11-15T21:00:00Z",
        "intervalParametersStartTime": "2025-11-15T20:00:00Z",
        "data": {
          "air_temperature": -4.3,
          "wind_from_direction": 296,
          "wind_speed": 1.9,
          "wind_speed_of_gust": 5,
          "relative_humidity": 81,
          "air_pressure_at_mean_sea_level": 992.4,
          "visibility_in_air": 75,
          "thunderstorm_probability": 0,
          "probability_of_frozen_precipitation": 0,
          "cloud_area_fraction": 4,
          "low_type_cloud_area_fraction": 4,
          "medium_type_cloud_area_fraction": 0,
          "high_type_cloud_area_fraction": 0,
          "cloud_base_altitude": 9999,
          "cloud_top_altitude": 9999,
          "mtpr": 0,
          "precipitation_amount_mean": 0,
          "precipitation_amount_min": 0,
          "precipitation_amount_max": 0,
          "precipitation_amount_median": 0,
          "probability_of_precipitation": 0,
          "precipitation_frozen_part": -9,
          "predominant_precipitation_type_at_surface": 0,
          "symbol_code": 3
        }
      },
      {
        "time": "2025-11-15T22:00:00Z",
        "intervalParametersStartTime": "2025-11-15T21:00:00Z",
        "data": {
          "air_temperature": -5.4,
          "wind_from_direction": 187,
          "wind_speed": 1.5,
          "wind_speed_of_gust": 3.4,
          "relative_humidity": 83,
          "air_pressure_at_mean_sea_level": 993.1,
          "visibility_in_air": 75,
          "thunderstorm_probability": 0,
          "probability_of_frozen_precipitation": 0,
          "cloud_area_fraction": 3,
          "low_type_cloud_area_fraction": 2,
          "medium_type_cloud_area_fraction": 0,
          "high_type_cloud_area_fraction": 0,
          "cloud_base_altitude": 9999,
          "cloud_top_altitude": 9999,
          "mtpr": 0,
          "precipitation_amount_mean": 0,
          "precipitation_amount_min": 0,
          "precipitation_amount_max": 0,
          "precipitation_amount_median": 0,
          "probability_of_precipitation": 0,
          "precipitation_frozen_part": -9,
          "predominant_precipitation_type_at_surface": 0,
          "symbol_code": 2
        }
      },
      {
        "time": "2025-11-15T23:00:00Z",
        "intervalParametersStartTime": "2025-11-15T22:00:00Z",
        "data": {
          "air_temperature": -5.8,
          "wind_from_direction": 171,
          "wind_speed": 1.8,
          "wind_speed_of_gust": 3.2,
          "relative_humidity": 84,
          "air_pressure_at_mean_sea_level": 993.5,
          "visibility_in_air": 25.9,
          "thunderstorm_probability": 0,
          "probability_of_frozen_precipitation": 0,
          "cloud_area_fraction": 3,
          "low_type_cloud_area_fraction": 2,
          "medium_type_cloud_area_fraction": 0,
          "high_type_cloud_area_fraction": 1,
          "cloud_base_altitude": 9999,
          "cloud_top_altitude": 9999,
          "mtpr": 0,
          "precipitation_amount_mean": 0,
          "precipitation_amount_min": 0.3,
          "precipitation_amount_max": 0.3,
          "precipitation_amount_median": 0,
          "probability_of_precipitation": 3,
          "precipitation_frozen_part": 1,
          "predominant_precipitation_type_at_surface": 5,
          "symbol_code": 2
        }
      },
      {
        "time": "2025-11-16T00:00:00Z",
        "intervalParametersStartTime": "2025-11-15T23:00:00Z",
        "data": {
          "air_temperature": -5.9,
          "wind_from_direction": 187,
          "wind_speed": 1.9,
          "wind_speed_of_gust": 3.3,
          "relative_humidity": 81,
          "air_pressure_at_mean_sea_level": 993.5,
          "visibility_in_air": 29.1,
          "thunderstorm_probability": 0,
          "probability_of_frozen_precipitation": 0,
          "cloud_area_fraction": 3,
          "low_type_cloud_area_fraction": 1,
          "medium_type_cloud_area_fraction": 0,
          "high_type_cloud_area_fraction": 1,
          "cloud_base_altitude": 9999,
          "cloud_top_altitude": 9999,
          "mtpr": 0,
          "precipitation_amount_mean": 0,
          "precipitation_amount_min": 0.2,
          "precipitation_amount_max": 0.3,
          "precipitation_amount_median": 0,
          "probability_of_precipitation": 17,
          "precipitation_frozen_part": 1,
          "predominant_precipitation_type_at_surface": 5,
          "symbol_code": 2
        }
      },
      {
        "time": "2025-11-16T01:00:00Z",
        "intervalParametersStartTime": "2025-11-16T00:00:00Z",
        "data": {
          "air_temperature": -5.7,
          "wind_from_direction": 207,
          "wind_speed": 2.1,
          "wind_speed_of_gust": 4,
          "relative_humidity": 73,
          "air_pressure_at_mean_sea_level": 993.3,
          "visibility_in_air": 38.6,
          "thunderstorm_probability": 0,
          "probability_of_frozen_precipitation": 0,
          "cloud_area_fraction": 4,
          "low_type_cloud_area_fraction": 1,
          "medium_type_cloud_area_fraction": 1,
          "high_type_cloud_area_fraction": 2,
          "cloud_base_altitude": 9999,
          "cloud_top_altitude": 9999,
          "mtpr": 0,
          "precipitation_amount_mean": 0.1,
          "precipitation_amount_min": 0.1,
          "precipitation_amount_max": 0.7,
          "precipitation_amount_median": 0,
          "probability_of_precipitation": 14,
          "precipitation_frozen_part": 1,
          "predominant_precipitation_type_at_surface": 5,
          "symbol_code": 3
        }
      },
      {
        "time": "2025-11-16T02:00:00Z",
        "intervalParametersStartTime": "2025-11-16T01:00:00Z",
        "data": {
          "air_temperature": -5.9,
          "wind_from_direction": 196,
          "wind_speed": 1.8,
          "wind_speed_of_gust": 3.9,
          "relative_humidity": 71,
          "air_pressure_at_mean_sea_level": 992.8,
          "visibility_in_air": 40.8,
          "thunderstorm_probability": 0,
          "probability_of_frozen_precipitation": 0,
          "cloud_area_fraction": 5,
          "low_type_cloud_area_fraction": 2,
          "medium_type_cloud_area_fraction": 1,
          "high_type_cloud_area_fraction": 2,
          "cloud_base_altitude": 9999,
          "cloud_top_altitude": 9999,
          "mtpr": 0,
          "precipitation_amount_mean": 0.1,
          "precipitation_amount_min": 0.1,
          "precipitation_amount_max": 0.2,
          "precipitation_amount_median": 0,
          "probability_of_precipitation": 21,
          "precipitation_frozen_part": 1,
          "predominant_precipitation_type_at_surface": 5,
          "symbol_code": 3
        }
      },
      {
        "time": "2025-11-16T03:00:00Z",
        "intervalParametersStartTime": "2025-11-16T02:00:00Z",
        "data": {
          "air_temperature": -5.7,
          "wind_from_direction": 169,
          "wind_speed": 1.8,
          "wind_speed_of_gust": 3.4,
          "relative_humidity": 69,
          "air_pressure_at_mean_sea_level": 992.4,
          "visibility_in_air": 43.4,
          "thunderstorm_probability": 0,
          "probability_of_frozen_precipitation": 0,
          "cloud_area_fraction": 6,
          "low_type_cloud_area_fraction": 4,
          "medium_type_cloud_area_fraction": 3,
          "high_type_cloud_area_fraction": 1,
          "cloud_base_altitude": 9999,
          "cloud_top_altitude": 9999,
          "mtpr": 0,
          "precipitation_amount_mean": 0,
          "precipitation_amount_min": 0.1,
          "precipitation_amount_max": 0.1,
          "precipitation_amount_median": 0,
          "probability_of_precipitation": 24,
          "precipitation_frozen_part": 1,
          "predominant_precipitation_type_at_surface": 5,
          "symbol_code": 4
        }
      },
      {
        "time": "2025-11-16T04:00:00Z",
        "intervalParametersStartTime": "2025-11-16T03:00:00Z",
        "data": {
          "air_temperature": -5.5,
          "wind_from_direction": 147,
          "wind_speed": 1.7,
          "wind_speed_of_gust": 3.2,
          "relative_humidity": 67,
          "air_pressure_at_mean_sea_level": 991.8,
          "visibility_in_air": 45.8,
          "thunderstorm_probability": 0,
          "probability_of_frozen_precipitation": 0,
          "cloud_area_fraction": 7,
          "low_type_cloud_area_fraction": 6,
          "medium_type_cloud_area_fraction": 5,
          "high_type_cloud_area_fraction": 0,
          "cloud_base_altitude": 9999,
          "cloud_top_altitude": 9999,
          "mtpr": 0,
          "precipitation_amount_mean": 0,
          "precipitation_amount_min": 0.1,
          "precipitation_amount_max": 0.1,
          "precipitation_amount_median": 0,
          "probability_of_precipitation": 24,
          "precipitation_frozen_part": 1,
          "predominant_precipitation_type_at_surface": 5,
          "symbol_code": 4
        }
      },
      {
        "time": "2025-11-16T05:00:00Z",
        "intervalParametersStartTime": "2025-11-16T04:00:00Z",
        "data": {
          "air_temperature": -5.3,
          "wind_from_direction": 130,
          "wind_speed": 1.9,
          "wind_speed_of_gust": 3.3,
          "relative_humidity": 67,
          "air_pressure_at_mean_sea_level": 991.3,
          "visibility_in_air": 45.7,
          "thunderstorm_probability": 0,
          "probability_of_frozen_precipitation": 0,
          "cloud_area_fraction": 8,
          "low_type_cloud_area_fraction": 7,
          "medium_type_cloud_area_fraction": 6,
          "high_type_cloud_area_fraction": 0,
          "cloud_base_altitude": 9999,
          "cloud_top_altitude": 9999,
          "mtpr": 0,
          "precipitation_amount_mean": 0,
          "precipitation_amount_min": 0.1,
          "precipitation_amount_max": 0.1,
          "precipitation_amount_median": 0,
          "probability_of_precipitation": 28,
          "precipitation_frozen_part": 1,
          "predominant_precipitation_type_at_surface": 5,
          "symbol_code": 6
        }
      },
      {
        "time": "2025-11-16T06:00:00Z",
        "intervalParametersStartTime": "2025-11-16T05:00:00Z",
        "data": {
          "air_temperature": -5.1,
          "wind_from_direction": 111,
          "wind_speed": 1.9,
          "wind_speed_of_gust": 3.5,
          "relative_humidity": 67,
          "air_pressure_at_mean_sea_level": 990.9,
          "visibility_in_air": 45,
          "thunderstorm_probability": 0,
          "probability_of_frozen_precipitation": 0,
          "cloud_area_fraction": 8,
          "low_type_cloud_area_fraction": 8,
          "medium_type_cloud_area_fraction": 6,
          "high_type_cloud_area_fraction": 0,
          "cloud_base_altitude": 9999,
          "cloud_top_altitude": 9999,
          "mtpr": 0,
          "precipitation_amount_mean": 0,
          "precipitation_amount_min": 0.2,
          "precipitation_amount_max": 0.4,
          "precipitation_amount_median": 0,
          "probability_of_precipitation": 10,
          "precipitation_frozen_part": 1,
          "predominant_precipitation_type_at_surface": 5,
          "symbol_code": 6
        }
      },
      {
        "time": "2025-11-16T07:00:00Z",
        "intervalParametersStartTime": "2025-11-16T06:00:00Z",
        "data": {
          "air_temperature": -4.6,
          "wind_from_direction": 96,
          "wind_speed": 2,
          "wind_speed_of_gust": 5.5,
          "relative_humidity": 72,
          "air_pressure_at_mean_sea_level": 990.7,
          "visibility_in_air": 4.3,
          "thunderstorm_probability": 0,
          "probability_of_frozen_precipitation": 0,
          "cloud_area_fraction": 8,
          "low_type_cloud_area_fraction": 8,
          "medium_type_cloud_area_fraction": 6,
          "high_type_cloud_area_fraction": 0,
          "cloud_base_altitude": 9999,
          "cloud_top_altitude": 9999,
          "mtpr": 0,
          "precipitation_amount_mean": 0,
          "precipitation_amount_min": 0.1,
          "precipitation_amount_max": 0.5,
          "precipitation_amount_median": 0,
          "probability_of_precipitation": 17,
          "precipitation_frozen_part": 1,
          "predominant_precipitation_type_at_surface": 5,
          "symbol_code": 6
        }
      },
      {
        "time": "2025-11-16T08:00:00Z",
        "intervalParametersStartTime": "2025-11-16T07:00:00Z",
        "data": {
          "air_temperature": -4.6,
          "wind_from_direction": 93,
          "wind_speed": 1.9,
          "wind_speed_of_gust": 3.9,
          "relative_humidity": 78,
          "air_pressure_at_mean_sea_level": 990.7,
          "visibility_in_air": 3.2,
          "thunderstorm_probability": 0,
          "probability_of_frozen_precipitation": 0,
          "cloud_area_fraction": 8,
          "low_type_cloud_area_fraction": 8,
          "medium_type_cloud_area_fraction": 6,
          "high_type_cloud_area_fraction": 0,
          "cloud_base_altitude": 1519,
          "cloud_top_altitude": 4072,
          "mtpr": 0,
          "precipitation_amount_mean": 0,
          "precipitation_amount_min": 0.1,
          "precipitation_amount_max": 0.2,
          "precipitation_amount_median": 0,
          "probability_of_precipitation": 17,
          "precipitation_frozen_part": 1,
          "predominant_precipitation_type_at_surface": 5,
          "symbol_code": 6
        }
      },
      {
        "time": "2025-11-16T09:00:00Z",
        "intervalParametersStartTime": "2025-11-16T08:00:00Z",
        "data": {
          "air_temperature": -4.5,
          "wind_from_direction": 116,
          "wind_speed": 1.3,
          "wind_speed_of_gust": 3.6,
          "relative_humidity": 81,
          "air_pressure_at_mean_sea_level": 991,
          "visibility_in_air": 3.5,
          "thunderstorm_probability": 0.02,
          "probability_of_frozen_precipitation": 0.01,
          "cloud_area_fraction": 8,
          "low_type_cloud_area_fraction": 7,
          "medium_type_cloud_area_fraction": 4,
          "high_type_cloud_area_fraction": 0,
          "cloud_base_altitude": 1050,
          "cloud_top_altitude": 1267,
          "mtpr": 0,
          "precipitation_amount_mean": 0,
          "precipitation_amount_min": 0.2,
          "precipitation_amount_max": 0.3,
          "precipitation_amount_median": 0,
          "probability_of_precipitation": 10,
          "precipitation_frozen_part": 1,
          "predominant_precipitation_type_at_surface": 5,
          "symbol_code": 4
        }
      },
      {
        "time": "2025-11-16T10:00:00Z",
        "intervalParametersStartTime": "2025-11-16T09:00:00Z",
        "data": {
          "air_temperature": -4,
          "wind_from_direction": 299,
          "wind_speed": 0.8,
          "wind_speed_of_gust": 2.5,
          "relative_humidity": 85,
          "air_pressure_at_mean_sea_level": 991.8,
          "visibility_in_air": 25.4,
          "thunderstorm_probability": 0.01,
          "probability_of_frozen_precipitation": 0.01,
          "cloud_area_fraction": 6,
          "low_type_cloud_area_fraction": 6,
          "medium_type_cloud_area_fraction": 2,
          "high_type_cloud_area_fraction": 0,
          "cloud_base_altitude": 9999,
          "cloud_top_altitude": 9999,
          "mtpr": 0,
          "precipitation_amount_mean": 0,
          "precipitation_amount_min": 0.2,
          "precipitation_amount_max": 0.5,
          "precipitation_amount_median": 0,
          "probability_of_precipitation": 10,
          "precipitation_frozen_part": 1,
          "predominant_precipitation_type_at_surface": 5,
          "symbol_code": 4
        }
      },
      {
        "time": "2025-11-16T11:00:00Z",
        "intervalParametersStartTime": "2025-11-16T10:00:00Z",
        "data": {
          "air_temperature": -4.5,
          "wind_from_direction": 308,
          "wind_speed": 0.7,
          "wind_speed_of_gust": 1.9,
          "relative_humidity": 89,
          "air_pressure_at_mean_sea_level": 992,
          "visibility_in_air": 75,
          "thunderstorm_probability": 0,
          "probability_of_frozen_precipitation": 0,
          "cloud_area_fraction": 5,
          "low_type_cloud_area_fraction": 5,
          "medium_type_cloud_area_fraction": 0,
          "high_type_cloud_area_fraction": 0,
          "cloud_base_altitude": 9999,
          "cloud_top_altitude": 9999,
          "mtpr": 0,
          "precipitation_amount_mean": 0,
          "precipitation_amount_min": 0.2,
          "precipitation_amount_max": 0.5,
          "precipitation_amount_median": 0,
          "probability_of_precipitation": 10,
          "precipitation_frozen_part": 1,
          "predominant_precipitation_type_at_surface": 5,
          "symbol_code": 3
        }
      },
      {
        "time": "2025-11-16T12:00:00Z",
        "intervalParametersStartTime": "2025-11-16T11:00:00Z",
        "data": {
          "air_temperature": -5,
          "wind_from_direction": 254,
          "wind_speed": 1.8,
          "wind_speed_of_gust": 3.5,
          "relative_humidity": 74,
          "air_pressure_at_mean_sea_level": 992.2,
          "visibility_in_air": 37.6,
          "thunderstorm_probability": 0,
          "probability_of_frozen_precipitation": 0,
          "cloud_area_fraction": 4,
          "low_type_cloud_area_fraction": 3,
          "medium_type_cloud_area_fraction": 0,
          "high_type_cloud_area_fraction": 0,
          "cloud_base_altitude": 9999,
          "cloud_top_altitude": 9999,
          "mtpr": 0,
          "precipitation_amount_mean": 0,
          "precipitation_amount_min": 0.1,
          "precipitation_amount_max": 0.1,
          "precipitation_amount_median": 0,
          "probability_of_precipitation": 14,
          "precipitation_frozen_part": 1,
          "predominant_precipitation_type_at_surface": 5,
          "symbol_code": 3
        }
      },
      {
        "time": "2025-11-16T13:00:00Z",
        "intervalParametersStartTime": "2025-11-16T12:00:00Z",
        "data": {
          "air_temperature": -5.8,
          "wind_from_direction": 239,
          "wind_speed": 2.1,
          "wind_speed_of_gust": 4.4,
          "relative_humidity": 73,
          "air_pressure_at_mean_sea_level": 992.7,
          "visibility_in_air": 38.1,
          "thunderstorm_probability": 0,
          "probability_of_frozen_precipitation": 0,
          "cloud_area_fraction": 2,
          "low_type_cloud_area_fraction": 2,
          "medium_type_cloud_area_fraction": 0,
          "high_type_cloud_area_fraction": 0,
          "cloud_base_altitude": 9999,
          "cloud_top_altitude": 9999,
          "mtpr": 0,
          "precipitation_amount_mean": 0,
          "precipitation_amount_min": 0.2,
          "precipitation_amount_max": 0.3,
          "precipitation_amount_median": 0,
          "probability_of_precipitation": 10,
          "precipitation_frozen_part": 1,
          "predominant_precipitation_type_at_surface": 5,
          "symbol_code": 2
        }
      },
      {
        "time": "2025-11-16T14:00:00Z",
        "intervalParametersStartTime": "2025-11-16T13:00:00Z",
        "data": {
          "air_temperature": -6.5,
          "wind_from_direction": 196,
          "wind_speed": 1.9,
          "wind_speed_of_gust": 3.9,
          "relative_humidity": 76,
          "air_pressure_at_mean_sea_level": 993.3,
          "visibility_in_air": 34.9,
          "thunderstorm_probability": 0,
          "probability_of_frozen_precipitation": 0,
          "cloud_area_fraction": 2,
          "low_type_cloud_area_fraction": 1,
          "medium_type_cloud_area_fraction": 0,
          "high_type_cloud_area_fraction": 0,
          "cloud_base_altitude": 9999,
          "cloud_top_altitude": 9999,
          "mtpr": 0,
          "precipitation_amount_mean": 0,
          "precipitation_amount_min": 0.1,
          "precipitation_amount_max": 0.1,
          "precipitation_amount_median": 0,
          "probability_of_precipitation": 7,
          "precipitation_frozen_part": 1,
          "predominant_precipitation_type_at_surface": 5,
          "symbol_code": 2
        }
      },
      {
        "time": "2025-11-16T15:00:00Z",
        "intervalParametersStartTime": "2025-11-16T14:00:00Z",
        "data": {
          "air_temperature": -7.2,
          "wind_from_direction": 192,
          "wind_speed": 1.8,
          "wind_speed_of_gust": 3.8,
          "relative_humidity": 76,
          "air_pressure_at_mean_sea_level": 993.7,
          "visibility_in_air": 75,
          "thunderstorm_probability": 0,
          "probability_of_frozen_precipitation": 0,
          "cloud_area_fraction": 1,
          "low_type_cloud_area_fraction": 1,
          "medium_type_cloud_area_fraction": 0,
          "high_type_cloud_area_fraction": 0,
          "cloud_base_altitude": 9999,
          "cloud_top_altitude": 9999,
          "mtpr": 0,
          "precipitation_amount_mean": 0,
          "precipitation_amount_min": 0.1,
          "precipitation_amount_max": 0.1,
          "precipitation_amount_median": 0,
          "probability_of_precipitation": 3,
          "precipitation_frozen_part": 1,
          "predominant_precipitation_type_at_surface": 5,
          "symbol_code": 1
        }
      },
      {
        "time": "2025-11-16T16:00:00Z",
        "intervalParametersStartTime": "2025-11-16T15:00:00Z",
        "data": {
          "air_temperature": -7.9,
          "wind_from_direction": 190,
          "wind_speed": 1.8,
          "wind_speed_of_gust": 3.2,
          "relative_humidity": 76,
          "air_pressure_at_mean_sea_level": 994.3,
          "visibility_in_air": 75,
          "thunderstorm_probability": 0,
          "probability_of_frozen_precipitation": 0,
          "cloud_area_fraction": 0,
          "low_type_cloud_area_fraction": 0,
          "medium_type_cloud_area_fraction": 0,
          "high_type_cloud_area_fraction": 0,
          "cloud_base_altitude": 9999,
          "cloud_top_altitude": 9999,
          "mtpr": 0,
          "precipitation_amount_mean": 0,
          "precipitation_amount_min": 0.2,
          "precipitation_amount_max": 0.4,
          "precipitation_amount_median": 0,
          "probability_of_precipitation": 7,
          "precipitation_frozen_part": 1,
          "predominant_precipitation_type_at_surface": 5,
          "symbol_code": 1
        }
      },
      {
        "time": "2025-11-16T17:00:00Z",
        "intervalParametersStartTime": "2025-11-16T16:00:00Z",
        "data": {
          "air_temperature": -8.5,
          "wind_from_direction": 197,
          "wind_speed": 1.9,
          "wind_speed_of_gust": 3,
          "relative_humidity": 76,
          "air_pressure_at_mean_sea_level": 994.8,
          "visibility_in_air": 35.2,
          "thunderstorm_probability": 0,
          "probability_of_frozen_precipitation": 0,
          "cloud_area_fraction": 0,
          "low_type_cloud_area_fraction": 0,
          "medium_type_cloud_area_fraction": 0,
          "high_type_cloud_area_fraction": 0,
          "cloud_base_altitude": 9999,
          "cloud_top_altitude": 9999,
          "mtpr": 0,
          "precipitation_amount_mean": 0,
          "precipitation_amount_min": 0.5,
          "precipitation_amount_max": 0.5,
          "precipitation_amount_median": 0,
          "probability_of_precipitation": 3,
          "precipitation_frozen_part": 1,
          "predominant_precipitation_type_at_surface": 5,
          "symbol_code": 1
        }
      },
      {
        "time": "2025-11-16T18:00:00Z",
        "intervalParametersStartTime": "2025-11-16T17:00:00Z",
        "data": {
          "air_temperature": -8.8,
          "wind_from_direction": 205,
          "wind_speed": 1.9,
          "wind_speed_of_gust": 2.9,
          "relative_humidity": 75,
          "air_pressure_at_mean_sea_level": 995.5,
          "visibility_in_air": 36.1,
          "thunderstorm_probability": 0,
          "probability_of_frozen_precipitation": 0,
          "cloud_area_fraction": 0,
          "low_type_cloud_area_fraction": 0,
          "medium_type_cloud_area_fraction": 0,
          "high_type_cloud_area_fraction": 0,
          "cloud_base_altitude": 9999,
          "cloud_top_altitude": 9999,
          "mtpr": 0,
          "precipitation_amount_mean": 0,
          "precipitation_amount_min": 0.1,
          "precipitation_amount_max": 0.1,
          "precipitation_amount_median": 0,
          "probability_of_precipitation": 7,
          "precipitation_frozen_part": 1,
          "predominant_precipitation_type_at_surface": 5,
          "symbol_code": 1
        }
      },
      {
        "time": "2025-11-16T19:00:00Z",
        "intervalParametersStartTime": "2025-11-16T18:00:00Z",
        "data": {
          "air_temperature": -9,
          "wind_from_direction": 209,
          "wind_speed": 2,
          "wind_speed_of_gust": 3,
          "relative_humidity": 72,
          "air_pressure_at_mean_sea_level": 996.1,
          "visibility_in_air": 39.3,
          "thunderstorm_probability": 0,
          "probability_of_frozen_precipitation": 0,
          "cloud_area_fraction": 0,
          "low_type_cloud_area_fraction": 0,
          "medium_type_cloud_area_fraction": 0,
          "high_type_cloud_area_fraction": 0,
          "cloud_base_altitude": 9999,
          "cloud_top_altitude": 9999,
          "mtpr": 0,
          "precipitation_amount_mean": 0,
          "precipitation_amount_min": 0,
          "precipitation_amount_max": 0,
          "precipitation_amount_median": 0,
          "probability_of_precipitation": 0,
          "precipitation_frozen_part": -9,
          "predominant_precipitation_type_at_surface": 0,
          "symbol_code": 1
        }
      },
      {
        "time": "2025-11-16T20:00:00Z",
        "intervalParametersStartTime": "2025-11-16T19:00:00Z",
        "data": {
          "air_temperature": -9.4,
          "wind_from_direction": 213,
          "wind_speed": 1.8,
          "wind_speed_of_gust": 3,
          "relative_humidity": 73,
          "air_pressure_at_mean_sea_level": 996.8,
          "visibility_in_air": 38.4,
          "thunderstorm_probability": 0,
          "probability_of_frozen_precipitation": 0,
          "cloud_area_fraction": 0,
          "low_type_cloud_area_fraction": 0,
          "medium_type_cloud_area_fraction": 0,
          "high_type_cloud_area_fraction": 0,
          "cloud_base_altitude": 9999,
          "cloud_top_altitude": 9999,
          "mtpr": 0,
          "precipitation_amount_mean": 0,
          "precipitation_amount_min": 0.1,
          "precipitation_amount_max": 0.1,
          "precipitation_amount_median": 0,
          "probability_of_precipitation": 7,
          "precipitation_frozen_part": 1,
          "predominant_precipitation_type_at_surface": 5,
          "symbol_code": 1
        }
      },
      {
        "time": "2025-11-16T21:00:00Z",
        "intervalParametersStartTime": "2025-11-16T20:00:00Z",
        "data": {
          "air_temperature": -9.8,
          "wind_from_direction": 214,
          "wind_speed": 1.6,
          "wind_speed_of_gust": 2.6,
          "relative_humidity": 74,
          "air_pressure_at_mean_sea_level": 997.6,
          "visibility_in_air": 75,
          "thunderstorm_probability": 0,
          "probability_of_frozen_precipitation": 0,
          "cloud_area_fraction": 1,
          "low_type_cloud_area_fraction": 0,
          "medium_type_cloud_area_fraction": 0,
          "high_type_cloud_area_fraction": 1,
          "cloud_base_altitude": 9999,
          "cloud_top_altitude": 9999,
          "mtpr": 0,
          "precipitation_amount_mean": 0,
          "precipitation_amount_min": 0.1,
          "precipitation_amount_max": 0.1,
          "precipitation_amount_median": 0,
          "probability_of_precipitation": 3,
          "precipitation_frozen_part": 1,
          "predominant_precipitation_type_at_surface": 5,
          "symbol_code": 1
        }
      },
      {
        "time": "2025-11-16T22:00:00Z",
        "intervalParametersStartTime": "2025-11-16T21:00:00Z",
        "data": {
          "air_temperature": -9.9,
          "wind_from_direction": 211,
          "wind_speed": 1.7,
          "wind_speed_of_gust": 2.5,
          "relative_humidity": 73,
          "air_pressure_at_mean_sea_level": 998.3,
          "visibility_in_air": 38.9,
          "thunderstorm_probability": 0,
          "probability_of_frozen_precipitation": 0,
          "cloud_area_fraction": 3,
          "low_type_cloud_area_fraction": 0,
          "medium_type_cloud_area_fraction": 1,
          "high_type_cloud_area_fraction": 3,
          "cloud_base_altitude": 9999,
          "cloud_top_altitude": 9999,
          "mtpr": 0,
          "precipitation_amount_mean": 0,
          "precipitation_amount_min": 0.1,
          "precipitation_amount_max": 0.1,
          "precipitation_amount_median": 0,
          "probability_of_precipitation": 3,
          "precipitation_frozen_part": 1,
          "predominant_precipitation_type_at_surface": 5,
          "symbol_code": 2
        }
      },
      {
        "time": "2025-11-16T23:00:00Z",
        "intervalParametersStartTime": "2025-11-16T22:00:00Z",
        "data": {
          "air_temperature": -10.1,
          "wind_from_direction": 223,
          "wind_speed": 1.6,
          "wind_speed_of_gust": 2.8,
          "relative_humidity": 71,
          "air_pressure_at_mean_sea_level": 998.5,
          "visibility_in_air": 41,
          "thunderstorm_probability": 0,
          "probability_of_frozen_precipitation": 0,
          "cloud_area_fraction": 4,
          "low_type_cloud_area_fraction": 0,
          "medium_type_cloud_area_fraction": 1,
          "high_type_cloud_area_fraction": 3,
          "cloud_base_altitude": 9999,
          "cloud_top_altitude": 9999,
          "mtpr": 0,
          "precipitation_amount_mean": 0,
          "precipitation_amount_min": 0,
          "precipitation_amount_max": 0,
          "precipitation_amount_median": 0,
          "probability_of_precipitation": 0,
          "precipitation_frozen_part": -9,
          "predominant_precipitation_type_at_surface": 0,
          "symbol_code": 3
        }
      },
      {
        "time": "2025-11-17T00:00:00Z",
        "intervalParametersStartTime": "2025-11-16T23:00:00Z",
        "data": {
          "air_temperature": -9.5,
          "wind_from_direction": 212,
          "wind_speed": 2,
          "wind_speed_of_gust": 3.2,
          "relative_humidity": 71,
          "air_pressure_at_mean_sea_level": 998.5,
          "visibility_in_air": 40.4,
          "thunderstorm_probability": 0,
          "probability_of_frozen_precipitation": 0,
          "cloud_area_fraction": 5,
          "low_type_cloud_area_fraction": 0,
          "medium_type_cloud_area_fraction": 2,
          "high_type_cloud_area_fraction": 2,
          "cloud_base_altitude": 9999,
          "cloud_top_altitude": 9999,
          "mtpr": 0,
          "precipitation_amount_mean": 0,
          "precipitation_amount_min": 0.2,
          "precipitation_amount_max": 0.2,
          "precipitation_amount_median": 0,
          "probability_of_precipitation": 3,
          "precipitation_frozen_part": 1,
          "predominant_precipitation_type_at_surface": 5,
          "symbol_code": 3
        }
      },
      {
        "time": "2025-11-17T01:00:00Z",
        "intervalParametersStartTime": "2025-11-17T00:00:00Z",
        "data": {
          "air_temperature": -9,
          "wind_from_direction": 206,
          "wind_speed": 1.9,
          "wind_speed_of_gust": 3.1,
          "relative_humidity": 71,
          "air_pressure_at_mean_sea_level": 998.8,
          "visibility_in_air": 75,
          "thunderstorm_probability": 0,
          "probability_of_frozen_precipitation": 0,
          "cloud_area_fraction": 5,
          "low_type_cloud_area_fraction": 1,
          "medium_type_cloud_area_fraction": 4,
          "high_type_cloud_area_fraction": 1,
          "cloud_base_altitude": 9999,
          "cloud_top_altitude": 9999,
          "mtpr": 0,
          "precipitation_amount_mean": 0,
          "precipitation_amount_min": 0,
          "precipitation_amount_max": 0,
          "precipitation_amount_median": 0,
          "probability_of_precipitation": 0,
          "precipitation_frozen_part": -9,
          "predominant_precipitation_type_at_surface": 0,
          "symbol_code": 3
        }
      },
      {
        "time": "2025-11-17T02:00:00Z",
        "intervalParametersStartTime": "2025-11-17T01:00:00Z",
        "data": {
          "air_temperature": -7.9,
          "wind_from_direction": 206,
          "wind_speed": 2,
          "wind_speed_of_gust": 3.1,
          "relative_humidity": 66,
          "air_pressure_at_mean_sea_level": 998.9,
          "visibility_in_air": 46.2,
          "thunderstorm_probability": 0,
          "probability_of_frozen_precipitation": 0,
          "cloud_area_fraction": 7,
          "low_type_cloud_area_fraction": 3,
          "medium_type_cloud_area_fraction": 6,
          "high_type_cloud_area_fraction": 1,
          "cloud_base_altitude": 9999,
          "cloud_top_altitude": 9999,
          "mtpr": 0,
          "precipitation_amount_mean": 0,
          "precipitation_amount_min": 0.1,
          "precipitation_amount_max": 0.1,
          "precipitation_amount_median": 0,
          "probability_of_precipitation": 7,
          "precipitation_frozen_part": 1,
          "predominant_precipitation_type_at_surface": 5,
          "symbol_code": 4
        }
      },
      {
        "time": "2025-11-17T03:00:00Z",
        "intervalParametersStartTime": "2025-11-17T02:00:00Z",
        "data": {
          "air_temperature": -6,
          "wind_from_direction": 190,
          "wind_speed": 2,
          "wind_speed_of_gust": 3.4,
          "relative_humidity": 62,
          "air_pressure_at_mean_sea_level": 999.2,
          "visibility_in_air": 51.2,
          "thunderstorm_probability": 0,
          "probability_of_frozen_precipitation": 0,
          "cloud_area_fraction": 8,
          "low_type_cloud_area_fraction": 6,
          "medium_type_cloud_area_fraction": 7,
          "high_type_cloud_area_fraction": 1,
          "cloud_base_altitude": 9999,
          "cloud_top_altitude": 9999,
          "mtpr": 0,
          "precipitation_amount_mean": 0,
          "precipitation_amount_min": 0.1,
          "precipitation_amount_max": 0.1,
          "precipitation_amount_median": 0,
          "probability_of_precipitation": 3,
          "precipitation_frozen_part": 1,
          "predominant_precipitation_type_at_surface": 5,
          "symbol_code": 6
        }
      },
      {
        "time": "2025-11-17T04:00:00Z",
        "intervalParametersStartTime": "2025-11-17T03:00:00Z",
        "data": {
          "air_temperature": -4.8,
          "wind_from_direction": 180,
          "wind_speed": 2.7,
          "wind_speed_of_gust": 4.7,
          "relative_humidity": 64,
          "air_pressure_at_mean_sea_level": 999.8,
          "visibility_in_air": 75,
          "thunderstorm_probability": 0,
          "probability_of_frozen_precipitation": 0,
          "cloud_area_fraction": 8,
          "low_type_cloud_area_fraction": 6,
          "medium_type_cloud_area_fraction": 5,
          "high_type_cloud_area_fraction": 1,
          "cloud_base_altitude": 1156,
          "cloud_top_altitude": 1813,
          "mtpr": 0,
          "precipitation_amount_mean": 0,
          "precipitation_amount_min": 0.1,
          "precipitation_amount_max": 0.1,
          "precipitation_amount_median": 0,
          "probability_of_precipitation": 3,
          "precipitation_frozen_part": 1,
          "predominant_precipitation_type_at_surface": 5,
          "symbol_code": 4
        }
      },
      {
        "time": "2025-11-17T05:00:00Z",
        "intervalParametersStartTime": "2025-11-17T04:00:00Z",
        "data": {
          "air_temperature": -4.1,
          "wind_from_direction": 187,
          "wind_speed": 2.8,
          "wind_speed_of_gust": 5,
          "relative_humidity": 67,
          "air_pressure_at_mean_sea_level": 1000.2,
          "visibility_in_air": 45.8,
          "thunderstorm_probability": 0,
          "probability_of_frozen_precipitation": 0,
          "cloud_area_fraction": 7,
          "low_type_cloud_area_fraction": 6,
          "medium_type_cloud_area_fraction": 2,
          "high_type_cloud_area_fraction": 0,
          "cloud_base_altitude": 9999,
          "cloud_top_altitude": 9999,
          "mtpr": 0,
          "precipitation_amount_mean": 0,
          "precipitation_amount_min": 0.1,
          "precipitation_amount_max": 0.1,
          "precipitation_amount_median": 0,
          "probability_of_precipitation": 7,
          "precipitation_frozen_part": 1,
          "predominant_precipitation_type_at_surface": 5,
          "symbol_code": 4
        }
      },
      {
        "time": "2025-11-17T06:00:00Z",
        "intervalParametersStartTime": "2025-11-17T05:00:00Z",
        "data": {
          "air_temperature": -4.1,
          "wind_from_direction": 205,
          "wind_speed": 1.9,
          "wind_speed_of_gust": 5.1,
          "relative_humidity": 71,
          "air_pressure_at_mean_sea_level": 1000.6,
          "visibility_in_air": 41.1,
          "thunderstorm_probability": 0,
          "probability_of_frozen_precipitation": 0,
          "cloud_area_fraction": 6,
          "low_type_cloud_area_fraction": 6,
          "medium_type_cloud_area_fraction": 1,
          "high_type_cloud_area_fraction": 0,
          "cloud_base_altitude": 954,
          "cloud_top_altitude": 1052,
          "mtpr": 0,
          "precipitation_amount_mean": 0,
          "precipitation_amount_min": 0.1,
          "precipitation_amount_max": 0.1,
          "precipitation_amount_median": 0,
          "probability_of_precipitation": 10,
          "precipitation_frozen_part": 1,
          "predominant_precipitation_type_at_surface": 5,
          "symbol_code": 4
        }
      },
      {
        "time": "2025-11-17T07:00:00Z",
        "intervalParametersStartTime": "2025-11-17T06:00:00Z",
        "data": {
          "air_temperature": -4.2,
          "wind_from_direction": 208,
          "wind_speed": 1.3,
          "wind_speed_of_gust": 3.5,
          "relative_humidity": 75,
          "air_pressure_at_mean_sea_level": 1001.2,
          "visibility_in_air": 36.4,
          "thunderstorm_probability": 0,
          "probability_of_frozen_precipitation": 0,
          "cloud_area_fraction": 6,
          "low_type_cloud_area_fraction": 6,
          "medium_type_cloud_area_fraction": 1,
          "high_type_cloud_area_fraction": 0,
          "cloud_base_altitude": 704,
          "cloud_top_altitude": 954,
          "mtpr": 0,
          "precipitation_amount_mean": 0,
          "precipitation_amount_min": 0.1,
          "precipitation_amount_max": 0.1,
          "precipitation_amount_median": 0,
          "probability_of_precipitation": 14,
          "precipitation_frozen_part": 1,
          "predominant_precipitation_type_at_surface": 5,
          "symbol_code": 4
        }
      },
      {
        "time": "2025-11-17T08:00:00Z",
        "intervalParametersStartTime": "2025-11-17T07:00:00Z",
        "data": {
          "air_temperature": -4.2,
          "wind_from_direction": 220,
          "wind_speed": 1.4,
          "wind_speed_of_gust": 2.5,
          "relative_humidity": 77,
          "air_pressure_at_mean_sea_level": 1001.8,
          "visibility_in_air": 75,
          "thunderstorm_probability": 0,
          "probability_of_frozen_precipitation": 0,
          "cloud_area_fraction": 6,
          "low_type_cloud_area_fraction": 6,
          "medium_type_cloud_area_fraction": 1,
          "high_type_cloud_area_fraction": 0,
          "cloud_base_altitude": 9999,
          "cloud_top_altitude": 9999,
          "mtpr": 0,
          "precipitation_amount_mean": 0,
          "precipitation_amount_min": 0.1,
          "precipitation_amount_max": 0.1,
          "precipitation_amount_median": 0,
          "probability_of_precipitation": 21,
          "precipitation_frozen_part": 0.96,
          "predominant_precipitation_type_at_surface": 5,
          "symbol_code": 4
        }
      },
      {
        "time": "2025-11-17T09:00:00Z",
        "intervalParametersStartTime": "2025-11-17T08:00:00Z",
        "data": {
          "air_temperature": -4.4,
          "wind_from_direction": 219,
          "wind_speed": 1.4,
          "wind_speed_of_gust": 2.8,
          "relative_humidity": 80,
          "air_pressure_at_mean_sea_level": 1002.2,
          "visibility_in_air": 75,
          "thunderstorm_probability": 0,
          "probability_of_frozen_precipitation": 0,
          "cloud_area_fraction": 6,
          "low_type_cloud_area_fraction": 6,
          "medium_type_cloud_area_fraction": 0,
          "high_type_cloud_area_fraction": 0,
          "cloud_base_altitude": 9999,
          "cloud_top_altitude": 9999,
          "mtpr": 0,
          "precipitation_amount_mean": 0,
          "precipitation_amount_min": 0.1,
          "precipitation_amount_max": 0.2,
          "precipitation_amount_median": 0,
          "probability_of_precipitation": 21,
          "precipitation_frozen_part": 0.91,
          "predominant_precipitation_type_at_surface": 5,
          "symbol_code": 4
        }
      },
      {
        "time": "2025-11-17T10:00:00Z",
        "intervalParametersStartTime": "2025-11-17T09:00:00Z",
        "data": {
          "air_temperature": -4.3,
          "wind_from_direction": 230,
          "wind_speed": 1.4,
          "wind_speed_of_gust": 3,
          "relative_humidity": 79,
          "air_pressure_at_mean_sea_level": 1002.4,
          "visibility_in_air": 31.5,
          "thunderstorm_probability": 0,
          "probability_of_frozen_precipitation": 0,
          "cloud_area_fraction": 6,
          "low_type_cloud_area_fraction": 5,
          "medium_type_cloud_area_fraction": 0,
          "high_type_cloud_area_fraction": 1,
          "cloud_base_altitude": 9999,
          "cloud_top_altitude": 9999,
          "mtpr": 0,
          "precipitation_amount_mean": 0,
          "precipitation_amount_min": 0.1,
          "precipitation_amount_max": 0.1,
          "precipitation_amount_median": 0,
          "probability_of_precipitation": 7,
          "precipitation_frozen_part": 0.91,
          "predominant_precipitation_type_at_surface": 5,
          "symbol_code": 3
        }
      },
      {
        "time": "2025-11-17T11:00:00Z",
        "intervalParametersStartTime": "2025-11-17T10:00:00Z",
        "data": {
          "air_temperature": -4.5,
          "wind_from_direction": 205,
          "wind_speed": 1.4,
          "wind_speed_of_gust": 2.6,
          "relative_humidity": 80,
          "air_pressure_at_mean_sea_level": 1002.4,
          "visibility_in_air": 30.8,
          "thunderstorm_probability": 0,
          "probability_of_frozen_precipitation": 0,
          "cloud_area_fraction": 6,
          "low_type_cloud_area_fraction": 4,
          "medium_type_cloud_area_fraction": 0,
          "high_type_cloud_area_fraction": 3,
          "cloud_base_altitude": 9999,
          "cloud_top_altitude": 9999,
          "mtpr": 0,
          "precipitation_amount_mean": 0,
          "precipitation_amount_min": 0,
          "precipitation_amount_max": 0,
          "precipitation_amount_median": 0,
          "probability_of_precipitation": 0,
          "precipitation_frozen_part": 0.91,
          "predominant_precipitation_type_at_surface": 5,
          "symbol_code": 4
        }
      },
      {
        "time": "2025-11-17T12:00:00Z",
        "intervalParametersStartTime": "2025-11-17T11:00:00Z",
        "data": {
          "air_temperature": -4.9,
          "wind_from_direction": 201,
          "wind_speed": 1.2,
          "wind_speed_of_gust": 2.8,
          "relative_humidity": 77,
          "air_pressure_at_mean_sea_level": 1002.5,
          "visibility_in_air": 75,
          "thunderstorm_probability": 0,
          "probability_of_frozen_precipitation": 0,
          "cloud_area_fraction": 7,
          "low_type_cloud_area_fraction": 4,
          "medium_type_cloud_area_fraction": 1,
          "high_type_cloud_area_fraction": 6,
          "cloud_base_altitude": 8756,
          "cloud_top_altitude": 8756,
          "mtpr": 0,
          "precipitation_amount_mean": 0,
          "precipitation_amount_min": 0,
          "precipitation_amount_max": 0,
          "precipitation_amount_median": 0,
          "probability_of_precipitation": 0,
          "precipitation_frozen_part": -9,
          "predominant_precipitation_type_at_surface": 0,
          "symbol_code": 4
        }
      },
      {
        "time": "2025-11-17T13:00:00Z",
        "intervalParametersStartTime": "2025-11-17T12:00:00Z",
        "data": {
          "air_temperature": -5.6,
          "wind_from_direction": 203,
          "wind_speed": 1.1,
          "wind_speed_of_gust": 2.3,
          "relative_humidity": 77,
          "air_pressure_at_mean_sea_level": 1002.7,
          "visibility_in_air": 75,
          "thunderstorm_probability": 0,
          "probability_of_frozen_precipitation": 0,
          "cloud_area_fraction": 8,
          "low_type_cloud_area_fraction": 5,
          "medium_type_cloud_area_fraction": 2,
          "high_type_cloud_area_fraction": 8,
          "cloud_base_altitude": 6273,
          "cloud_top_altitude": 8748,
          "mtpr": 0,
          "precipitation_amount_mean": 0,
          "precipitation_amount_min": 0.1,
          "precipitation_amount_max": 0.1,
          "precipitation_amount_median": 0,
          "probability_of_precipitation": 7,
          "precipitation_frozen_part": 1,
          "predominant_precipitation_type_at_surface": 5,
          "symbol_code": 6
        }
      },
      {
        "time": "2025-11-17T14:00:00Z",
        "intervalParametersStartTime": "2025-11-17T13:00:00Z",
        "data": {
          "air_temperature": -5.5,
          "wind_from_direction": 202,
          "wind_speed": 1.2,
          "wind_speed_of_gust": 2.4,
          "relative_humidity": 77,
          "air_pressure_at_mean_sea_level": 1002.6,
          "visibility_in_air": 33.9,
          "thunderstorm_probability": 0,
          "probability_of_frozen_precipitation": 0,
          "cloud_area_fraction": 8,
          "low_type_cloud_area_fraction": 6,
          "medium_type_cloud_area_fraction": 3,
          "high_type_cloud_area_fraction": 8,
          "cloud_base_altitude": 6267,
          "cloud_top_altitude": 6632,
          "mtpr": 0,
          "precipitation_amount_mean": 0,
          "precipitation_amount_min": 0.1,
          "precipitation_amount_max": 0.1,
          "precipitation_amount_median": 0,
          "probability_of_precipitation": 10,
          "precipitation_frozen_part": 1,
          "predominant_precipitation_type_at_surface": 5,
          "symbol_code": 6
        }
      },
      {
        "time": "2025-11-17T15:00:00Z",
        "intervalParametersStartTime": "2025-11-17T14:00:00Z",
        "data": {
          "air_temperature": -5.2,
          "wind_from_direction": 201,
          "wind_speed": 0.9,
          "wind_speed_of_gust": 2.1,
          "relative_humidity": 81,
          "air_pressure_at_mean_sea_level": 1002.4,
          "visibility_in_air": 29.3,
          "thunderstorm_probability": 0,
          "probability_of_frozen_precipitation": 0,
          "cloud_area_fraction": 8,
          "low_type_cloud_area_fraction": 5,
          "medium_type_cloud_area_fraction": 4,
          "high_type_cloud_area_fraction": 6,
          "cloud_base_altitude": 6626,
          "cloud_top_altitude": 6626,
          "mtpr": 0,
          "precipitation_amount_mean": 0,
          "precipitation_amount_min": 0.1,
          "precipitation_amount_max": 0.1,
          "precipitation_amount_median": 0,
          "probability_of_precipitation": 3,
          "precipitation_frozen_part": 1,
          "predominant_precipitation_type_at_surface": 5,
          "symbol_code": 6
        }
      },
      {
        "time": "2025-11-17T16:00:00Z",
        "intervalParametersStartTime": "2025-11-17T15:00:00Z",
        "data": {
          "air_temperature": -5.2,
          "wind_from_direction": 180,
          "wind_speed": 1.5,
          "wind_speed_of_gust": 2.5,
          "relative_humidity": 82,
          "air_pressure_at_mean_sea_level": 1002.3,
          "visibility_in_air": 75,
          "thunderstorm_probability": 0,
          "probability_of_frozen_precipitation": 0,
          "cloud_area_fraction": 7,
          "low_type_cloud_area_fraction": 4,
          "medium_type_cloud_area_fraction": 4,
          "high_type_cloud_area_fraction": 3,
          "cloud_base_altitude": 9999,
          "cloud_top_altitude": 9999,
          "mtpr": 0,
          "precipitation_amount_mean": 0,
          "precipitation_amount_min": 0.1,
          "precipitation_amount_max": 0.1,
          "precipitation_amount_median": 0,
          "probability_of_precipitation": 7,
          "precipitation_frozen_part": 1,
          "predominant_precipitation_type_at_surface": 5,
          "symbol_code": 4
        }
      },
      {
        "time": "2025-11-17T17:00:00Z",
        "intervalParametersStartTime": "2025-11-17T16:00:00Z",
        "data": {
          "air_temperature": -5.4,
          "wind_from_direction": 183,
          "wind_speed": 1.5,
          "wind_speed_of_gust": 2.8,
          "relative_humidity": 75,
          "air_pressure_at_mean_sea_level": 1002,
          "visibility_in_air": 75,
          "thunderstorm_probability": 0,
          "probability_of_frozen_precipitation": 0,
          "cloud_area_fraction": 7,
          "low_type_cloud_area_fraction": 3,
          "medium_type_cloud_area_fraction": 5,
          "high_type_cloud_area_fraction": 2,
          "cloud_base_altitude": 9999,
          "cloud_top_altitude": 9999,
          "mtpr": 0,
          "precipitation_amount_mean": 0,
          "precipitation_amount_min": 0.1,
          "precipitation_amount_max": 0.1,
          "precipitation_amount_median": 0,
          "probability_of_precipitation": 14,
          "precipitation_frozen_part": 1,
          "predominant_precipitation_type_at_surface": 5,
          "symbol_code": 4
        }
      },
      {
        "time": "2025-11-17T18:00:00Z",
        "intervalParametersStartTime": "2025-11-17T17:00:00Z",
        "data": {
          "air_temperature": -5.7,
          "wind_from_direction": 184,
          "wind_speed": 1.5,
          "wind_speed_of_gust": 2.8,
          "relative_humidity": 75,
          "air_pressure_at_mean_sea_level": 1002.1,
          "visibility_in_air": 75,
          "thunderstorm_probability": 0,
          "probability_of_frozen_precipitation": 0,
          "cloud_area_fraction": 7,
          "low_type_cloud_area_fraction": 4,
          "medium_type_cloud_area_fraction": 6,
          "high_type_cloud_area_fraction": 1,
          "cloud_base_altitude": 9999,
          "cloud_top_altitude": 9999,
          "mtpr": 0,
          "precipitation_amount_mean": 0,
          "precipitation_amount_min": 0.1,
          "precipitation_amount_max": 0.1,
          "precipitation_amount_median": 0,
          "probability_of_precipitation": 10,
          "precipitation_frozen_part": 1,
          "predominant_precipitation_type_at_surface": 5,
          "symbol_code": 4
        }
      },
      {
        "time": "2025-11-17T19:00:00Z",
        "intervalParametersStartTime": "2025-11-17T18:00:00Z",
        "data": {
          "air_temperature": -5.3,
          "wind_from_direction": 197,
          "wind_speed": 1,
          "wind_speed_of_gust": 2.7,
          "relative_humidity": 73,
          "air_pressure_at_mean_sea_level": 1002.2,
          "visibility_in_air": 75,
          "thunderstorm_probability": 0,
          "probability_of_frozen_precipitation": 0,
          "cloud_area_fraction": 8,
          "low_type_cloud_area_fraction": 6,
          "medium_type_cloud_area_fraction": 7,
          "high_type_cloud_area_fraction": 3,
          "cloud_base_altitude": 9999,
          "cloud_top_altitude": 9999,
          "mtpr": 0,
          "precipitation_amount_mean": 0,
          "precipitation_amount_min": 0.1,
          "precipitation_amount_max": 0.1,
          "precipitation_amount_median": 0,
          "probability_of_precipitation": 7,
          "precipitation_frozen_part": 1,
          "predominant_precipitation_type_at_surface": 5,
          "symbol_code": 6
        }
      },
      {
        "time": "2025-11-17T20:00:00Z",
        "intervalParametersStartTime": "2025-11-17T19:00:00Z",
        "data": {
          "air_temperature": -4.6,
          "wind_from_direction": 206,
          "wind_speed": 0.9,
          "wind_speed_of_gust": 1.8,
          "relative_humidity": 75,
          "air_pressure_at_mean_sea_level": 1002.1,
          "visibility_in_air": 75,
          "thunderstorm_probability": 0,
          "probability_of_frozen_precipitation": 0,
          "cloud_area_fraction": 8,
          "low_type_cloud_area_fraction": 6,
          "medium_type_cloud_area_fraction": 6,
          "high_type_cloud_area_fraction": 3,
          "cloud_base_altitude": 9999,
          "cloud_top_altitude": 9999,
          "mtpr": 0,
          "precipitation_amount_mean": 0.1,
          "precipitation_amount_min": 0.1,
          "precipitation_amount_max": 0.2,
          "precipitation_amount_median": 0,
          "probability_of_precipitation": 49,
          "precipitation_frozen_part": 1,
          "predominant_precipitation_type_at_surface": 5,
          "symbol_code": 6
        }
      },
      {
        "time": "2025-11-17T21:00:00Z",
        "intervalParametersStartTime": "2025-11-17T20:00:00Z",
        "data": {
          "air_temperature": -6.6,
          "wind_from_direction": 163,
          "wind_speed": 0.6,
          "wind_speed_of_gust": 1.5,
          "relative_humidity": 79,
          "air_pressure_at_mean_sea_level": 1001.9,
          "visibility_in_air": 75,
          "thunderstorm_probability": 0,
          "probability_of_frozen_precipitation": 0,
          "cloud_area_fraction": 8,
          "low_type_cloud_area_fraction": 7,
          "medium_type_cloud_area_fraction": 5,
          "high_type_cloud_area_fraction": 4,
          "cloud_base_altitude": 9999,
          "cloud_top_altitude": 9999,
          "mtpr": 0,
          "precipitation_amount_mean": 0.1,
          "precipitation_amount_min": 0.1,
          "precipitation_amount_max": 0.2,
          "precipitation_amount_median": 0,
          "probability_of_precipitation": 45,
          "precipitation_frozen_part": 1,
          "predominant_precipitation_type_at_surface": 5,
          "symbol_code": 6
        }
      },
      {
        "time": "2025-11-18T00:00:00Z",
        "intervalParametersStartTime": "2025-11-17T21:00:00Z",
        "data": {
          "air_temperature": -6.7,
          "wind_from_direction": 280,
          "wind_speed": 1.7,
          "wind_speed_of_gust": 4.8,
          "relative_humidity": 85,
          "air_pressure_at_mean_sea_level": 1002.5,
          "visibility_in_air": 7.8,
          "thunderstorm_probability": 0,
          "probability_of_frozen_precipitation": 0,
          "cloud_area_fraction": 8,
          "low_type_cloud_area_fraction": 8,
          "medium_type_cloud_area_fraction": 7,
          "high_type_cloud_area_fraction": 0,
          "cloud_base_altitude": 187,
          "cloud_top_altitude": 2931,
          "mtpr": 0,
          "precipitation_amount_mean": 0,
          "precipitation_amount_min": 0,
          "precipitation_amount_max": 0.1,
          "precipitation_amount_median": 0,
          "probability_of_precipitation": 34,
          "precipitation_frozen_part": 1,
          "predominant_precipitation_type_at_surface": 5,
          "symbol_code": 6
        }
      },
      {
        "time": "2025-11-18T06:00:00Z",
        "intervalParametersStartTime": "2025-11-18T00:00:00Z",
        "data": {
          "air_temperature": -6.9,
          "wind_from_direction": 279,
          "wind_speed": 2.3,
          "wind_speed_of_gust": 5.6,
          "relative_humidity": 82,
          "air_pressure_at_mean_sea_level": 1002.3,
          "visibility_in_air": 8.9,
          "thunderstorm_probability": 0,
          "probability_of_frozen_precipitation": 0,
          "cloud_area_fraction": 8,
          "low_type_cloud_area_fraction": 8,
          "medium_type_cloud_area_fraction": 3,
          "high_type_cloud_area_fraction": 0,
          "cloud_base_altitude": 347,
          "cloud_top_altitude": 795,
          "mtpr": 0,
          "precipitation_amount_mean": 0.1,
          "precipitation_amount_min": 0.4,
          "precipitation_amount_max": 0.6,
          "precipitation_amount_median": 0,
          "probability_of_precipitation": 11,
          "precipitation_frozen_part": 1,
          "predominant_precipitation_type_at_surface": 5,
          "symbol_code": 6
        }
      },
      {
        "time": "2025-11-18T12:00:00Z",
        "intervalParametersStartTime": "2025-11-18T06:00:00Z",
        "data": {
          "air_temperature": -7.4,
          "wind_from_direction": 282,
          "wind_speed": 3,
          "wind_speed_of_gust": 7,
          "relative_humidity": 89,
          "air_pressure_at_mean_sea_level": 1002.7,
          "visibility_in_air": 11.3,
          "thunderstorm_probability": 0,
          "probability_of_frozen_precipitation": 0,
          "cloud_area_fraction": 8,
          "low_type_cloud_area_fraction": 8,
          "medium_type_cloud_area_fraction": 1,
          "high_type_cloud_area_fraction": 2,
          "cloud_base_altitude": 99,
          "cloud_top_altitude": 639,
          "mtpr": 0,
          "precipitation_amount_mean": 0.1,
          "precipitation_amount_min": 0.4,
          "precipitation_amount_max": 0.7,
          "precipitation_amount_median": 0,
          "probability_of_precipitation": 22,
          "precipitation_frozen_part": 1,
          "predominant_precipitation_type_at_surface": 5,
          "symbol_code": 6
        }
      },
      {
        "time": "2025-11-18T18:00:00Z",
        "intervalParametersStartTime": "2025-11-18T12:00:00Z",
        "data": {
          "air_temperature": -7.6,
          "wind_from_direction": 267,
          "wind_speed": 2.6,
          "wind_speed_of_gust": 6.5,
          "relative_humidity": 85,
          "air_pressure_at_mean_sea_level": 1002.6,
          "visibility_in_air": 5.3,
          "thunderstorm_probability": 0,
          "probability_of_frozen_precipitation": 0,
          "cloud_area_fraction": 8,
          "low_type_cloud_area_fraction": 8,
          "medium_type_cloud_area_fraction": 8,
          "high_type_cloud_area_fraction": 3,
          "cloud_base_altitude": 259,
          "cloud_top_altitude": 2535,
          "mtpr": 0,
          "precipitation_amount_mean": 0.2,
          "precipitation_amount_min": 0.4,
          "precipitation_amount_max": 1.1,
          "precipitation_amount_median": 0,
          "probability_of_precipitation": 24,
          "precipitation_frozen_part": 0.94,
          "predominant_precipitation_type_at_surface": 5,
          "symbol_code": 6
        }
      },
      {
        "time": "2025-11-19T00:00:00Z",
        "intervalParametersStartTime": "2025-11-18T18:00:00Z",
        "data": {
          "air_temperature": -8,
          "wind_from_direction": 276,
          "wind_speed": 1.8,
          "wind_speed_of_gust": 5,
          "relative_humidity": 86,
          "air_pressure_at_mean_sea_level": 1003.8,
          "visibility_in_air": 14.7,
          "thunderstorm_probability": 0,
          "probability_of_frozen_precipitation": 0,
          "cloud_area_fraction": 8,
          "low_type_cloud_area_fraction": 8,
          "medium_type_cloud_area_fraction": 8,
          "high_type_cloud_area_fraction": 6,
          "cloud_base_altitude": 399,
          "cloud_top_altitude": 5795,
          "mtpr": 0,
          "precipitation_amount_mean": 0.2,
          "precipitation_amount_min": 0.4,
          "precipitation_amount_max": 1,
          "precipitation_amount_median": 0,
          "probability_of_precipitation": 24,
          "precipitation_frozen_part": 1,
          "predominant_precipitation_type_at_surface": 5,
          "symbol_code": 6
        }
      },
      {
        "time": "2025-11-19T06:00:00Z",
        "intervalParametersStartTime": "2025-11-19T00:00:00Z",
        "data": {
          "air_temperature": -8.2,
          "wind_from_direction": 276,
          "wind_speed": 1.7,
          "wind_speed_of_gust": 4.3,
          "relative_humidity": 86,
          "air_pressure_at_mean_sea_level": 1004.6,
          "visibility_in_air": 25.8,
          "thunderstorm_probability": 0,
          "probability_of_frozen_precipitation": 0,
          "cloud_area_fraction": 8,
          "low_type_cloud_area_fraction": 7,
          "medium_type_cloud_area_fraction": 8,
          "high_type_cloud_area_fraction": 0,
          "cloud_base_altitude": 303,
          "cloud_top_altitude": 5543,
          "mtpr": 0,
          "precipitation_amount_mean": 0.1,
          "precipitation_amount_min": 0.3,
          "precipitation_amount_max": 0.7,
          "precipitation_amount_median": 0,
          "probability_of_precipitation": 21,
          "precipitation_frozen_part": 1,
          "predominant_precipitation_type_at_surface": 5,
          "symbol_code": 6
        }
      },
      {
        "time": "2025-11-19T12:00:00Z",
        "intervalParametersStartTime": "2025-11-19T06:00:00Z",
        "data": {
          "air_temperature": -11.3,
          "wind_from_direction": 245,
          "wind_speed": 1.9,
          "wind_speed_of_gust": 5.3,
          "relative_humidity": 89,
          "air_pressure_at_mean_sea_level": 1006.8,
          "visibility_in_air": 0.1,
          "thunderstorm_probability": 0,
          "probability_of_frozen_precipitation": 0,
          "cloud_area_fraction": 8,
          "low_type_cloud_area_fraction": 8,
          "medium_type_cloud_area_fraction": 1,
          "high_type_cloud_area_fraction": 0,
          "cloud_base_altitude": 11,
          "cloud_top_altitude": 71,
          "mtpr": 0,
          "precipitation_amount_mean": 0.1,
          "precipitation_amount_min": 0.4,
          "precipitation_amount_max": 0.5,
          "precipitation_amount_median": 0,
          "probability_of_precipitation": 12,
          "precipitation_frozen_part": 1,
          "predominant_precipitation_type_at_surface": 5,
          "symbol_code": 7
        }
      },
      {
        "time": "2025-11-19T18:00:00Z",
        "intervalParametersStartTime": "2025-11-19T12:00:00Z",
        "data": {
          "air_temperature": -11.2,
          "wind_from_direction": 235,
          "wind_speed": 2.1,
          "wind_speed_of_gust": 5.7,
          "relative_humidity": 89,
          "air_pressure_at_mean_sea_level": 1008.5,
          "visibility_in_air": 0.1,
          "thunderstorm_probability": 0,
          "probability_of_frozen_precipitation": 0,
          "cloud_area_fraction": 8,
          "low_type_cloud_area_fraction": 8,
          "medium_type_cloud_area_fraction": 8,
          "high_type_cloud_area_fraction": 0,
          "cloud_base_altitude": 11,
          "cloud_top_altitude": 5063,
          "mtpr": 0,
          "precipitation_amount_mean": 0.1,
          "precipitation_amount_min": 0.5,
          "precipitation_amount_max": 0.8,
          "precipitation_amount_median": 0,
          "probability_of_precipitation": 10,
          "precipitation_frozen_part": 1,
          "predominant_precipitation_type_at_surface": 5,
          "symbol_code": 7
        }
      },
      {
        "time": "2025-11-20T00:00:00Z",
        "intervalParametersStartTime": "2025-11-19T18:00:00Z",
        "data": {
          "air_temperature": -8.7,
          "wind_from_direction": 250,
          "wind_speed": 1.8,
          "wind_speed_of_gust": 5.5,
          "relative_humidity": 90,
          "air_pressure_at_mean_sea_level": 1009.9,
          "visibility_in_air": 24.5,
          "thunderstorm_probability": 0,
          "probability_of_frozen_precipitation": 0,
          "cloud_area_fraction": 8,
          "low_type_cloud_area_fraction": 8,
          "medium_type_cloud_area_fraction": 1,
          "high_type_cloud_area_fraction": 0,
          "cloud_base_altitude": 27,
          "cloud_top_altitude": 643,
          "mtpr": 0,
          "precipitation_amount_mean": 0.2,
          "precipitation_amount_min": 0.1,
          "precipitation_amount_max": 0.3,
          "precipitation_amount_median": 0.1,
          "probability_of_precipitation": 60,
          "precipitation_frozen_part": 1,
          "predominant_precipitation_type_at_surface": 5,
          "symbol_code": 25
        }
      },
      {
        "time": "2025-11-20T06:00:00Z",
        "intervalParametersStartTime": "2025-11-20T00:00:00Z",
        "data": {
          "air_temperature": -6.9,
          "wind_from_direction": 222,
          "wind_speed": 1.7,
          "wind_speed_of_gust": 4.8,
          "relative_humidity": 87,
          "air_pressure_at_mean_sea_level": 1010.3,
          "visibility_in_air": 12.1,
          "thunderstorm_probability": 0,
          "probability_of_frozen_precipitation": 0.01,
          "cloud_area_fraction": 8,
          "low_type_cloud_area_fraction": 8,
          "medium_type_cloud_area_fraction": 3,
          "high_type_cloud_area_fraction": 0,
          "cloud_base_altitude": 511,
          "cloud_top_altitude": 1431,
          "mtpr": 0,
          "precipitation_amount_mean": 0,
          "precipitation_amount_min": 0.6,
          "precipitation_amount_max": 0.7,
          "precipitation_amount_median": 0,
          "probability_of_precipitation": 3,
          "precipitation_frozen_part": 0.94,
          "predominant_precipitation_type_at_surface": 5,
          "symbol_code": 6
        }
      },
      {
        "time": "2025-11-20T12:00:00Z",
        "intervalParametersStartTime": "2025-11-20T06:00:00Z",
        "data": {
          "air_temperature": -6,
          "wind_from_direction": 262,
          "wind_speed": 1.8,
          "wind_speed_of_gust": 5.2,
          "relative_humidity": 83,
          "air_pressure_at_mean_sea_level": 1011.3,
          "visibility_in_air": 9.7,
          "thunderstorm_probability": 0.01,
          "probability_of_frozen_precipitation": 0.01,
          "cloud_area_fraction": 8,
          "low_type_cloud_area_fraction": 8,
          "medium_type_cloud_area_fraction": 8,
          "high_type_cloud_area_fraction": 4,
          "cloud_base_altitude": 263,
          "cloud_top_altitude": 4579,
          "mtpr": 0,
          "precipitation_amount_mean": 0.1,
          "precipitation_amount_min": 1.2,
          "precipitation_amount_max": 1.4,
          "precipitation_amount_median": 0,
          "probability_of_precipitation": 4,
          "precipitation_frozen_part": 1,
          "predominant_precipitation_type_at_surface": 5,
          "symbol_code": 6
        }
      },
      {
        "time": "2025-11-20T18:00:00Z",
        "intervalParametersStartTime": "2025-11-20T12:00:00Z",
        "data": {
          "air_temperature": -6.8,
          "wind_from_direction": 266,
          "wind_speed": 1.9,
          "wind_speed_of_gust": 5.8,
          "relative_humidity": 84,
          "air_pressure_at_mean_sea_level": 1012,
          "visibility_in_air": 46.6,
          "thunderstorm_probability": 0,
          "probability_of_frozen_precipitation": 0,
          "cloud_area_fraction": 8,
          "low_type_cloud_area_fraction": 8,
          "medium_type_cloud_area_fraction": 2,
          "high_type_cloud_area_fraction": 0,
          "cloud_base_altitude": 351,
          "cloud_top_altitude": 719,
          "mtpr": 0,
          "precipitation_amount_mean": 0,
          "precipitation_amount_min": 0.8,
          "precipitation_amount_max": 1,
          "precipitation_amount_median": 0,
          "probability_of_precipitation": 5,
          "precipitation_frozen_part": 1,
          "predominant_precipitation_type_at_surface": 5,
          "symbol_code": 6
        }
      },
      {
        "time": "2025-11-21T00:00:00Z",
        "intervalParametersStartTime": "2025-11-20T18:00:00Z",
        "data": {
          "air_temperature": -10.2,
          "wind_from_direction": 221,
          "wind_speed": 1.8,
          "wind_speed_of_gust": 5.2,
          "relative_humidity": 90,
          "air_pressure_at_mean_sea_level": 1012.7,
          "visibility_in_air": 0.1,
          "thunderstorm_probability": 0,
          "probability_of_frozen_precipitation": 0,
          "cloud_area_fraction": 8,
          "low_type_cloud_area_fraction": 8,
          "medium_type_cloud_area_fraction": 6,
          "high_type_cloud_area_fraction": 0,
          "cloud_base_altitude": 11,
          "cloud_top_altitude": 4563,
          "mtpr": 0,
          "precipitation_amount_mean": 0,
          "precipitation_amount_min": 0.6,
          "precipitation_amount_max": 1.1,
          "precipitation_amount_median": 0,
          "probability_of_precipitation": 6,
          "precipitation_frozen_part": 1,
          "predominant_precipitation_type_at_surface": 5,
          "symbol_code": 7
        }
      },
      {
        "time": "2025-11-21T06:00:00Z",
        "intervalParametersStartTime": "2025-11-21T00:00:00Z",
        "data": {
          "air_temperature": -12.3,
          "wind_from_direction": 228,
          "wind_speed": 1.1,
          "wind_speed_of_gust": 4.5,
          "relative_humidity": 88,
          "air_pressure_at_mean_sea_level": 1012,
          "visibility_in_air": 0.2,
          "thunderstorm_probability": 0,
          "probability_of_frozen_precipitation": 0.01,
          "cloud_area_fraction": 7,
          "low_type_cloud_area_fraction": 7,
          "medium_type_cloud_area_fraction": 2,
          "high_type_cloud_area_fraction": 0,
          "cloud_base_altitude": 11,
          "cloud_top_altitude": 95,
          "mtpr": 0,
          "precipitation_amount_mean": 0.1,
          "precipitation_amount_min": 1.1,
          "precipitation_amount_max": 1.5,
          "precipitation_amount_median": 0,
          "probability_of_precipitation": 5,
          "precipitation_frozen_part": 1,
          "predominant_precipitation_type_at_surface": 5,
          "symbol_code": 7
        }
      },
      {
        "time": "2025-11-21T12:00:00Z",
        "intervalParametersStartTime": "2025-11-21T06:00:00Z",
        "data": {
          "air_temperature": -13.1,
          "wind_from_direction": 257,
          "wind_speed": 0.8,
          "wind_speed_of_gust": 3.9,
          "relative_humidity": 82,
          "air_pressure_at_mean_sea_level": 1012.4,
          "visibility_in_air": 0.2,
          "thunderstorm_probability": 0,
          "probability_of_frozen_precipitation": 0,
          "cloud_area_fraction": 6,
          "low_type_cloud_area_fraction": 6,
          "medium_type_cloud_area_fraction": 0,
          "high_type_cloud_area_fraction": 0,
          "cloud_base_altitude": 11,
          "cloud_top_altitude": 123,
          "mtpr": 0,
          "precipitation_amount_mean": 0,
          "precipitation_amount_min": 0.6,
          "precipitation_amount_max": 1,
          "precipitation_amount_median": 0,
          "probability_of_precipitation": 6,
          "precipitation_frozen_part": 1,
          "predominant_precipitation_type_at_surface": 5,
          "symbol_code": 7
        }
      },
      {
        "time": "2025-11-22T00:00:00Z",
        "intervalParametersStartTime": "2025-11-21T12:00:00Z",
        "data": {
          "air_temperature": -11.4,
          "wind_from_direction": 165,
          "wind_speed": 1.3,
          "wind_speed_of_gust": 4.9,
          "relative_humidity": 85,
          "air_pressure_at_mean_sea_level": 1010.8,
          "visibility_in_air": 1.3,
          "thunderstorm_probability": 0,
          "probability_of_frozen_precipitation": 0,
          "cloud_area_fraction": 7,
          "low_type_cloud_area_fraction": 6,
          "medium_type_cloud_area_fraction": 3,
          "high_type_cloud_area_fraction": 2,
          "cloud_base_altitude": 2341,
          "cloud_top_altitude": 4604,
          "mtpr": 0,
          "precipitation_amount_mean": 0.3,
          "precipitation_amount_min": 1.3,
          "precipitation_amount_max": 3,
          "precipitation_amount_median": 0,
          "probability_of_precipitation": 16,
          "precipitation_frozen_part": 0.94,
          "predominant_precipitation_type_at_surface": 5,
          "symbol_code": 4
        }
      },
      {
        "time": "2025-11-22T12:00:00Z",
        "intervalParametersStartTime": "2025-11-22T00:00:00Z",
        "data": {
          "air_temperature": -11.1,
          "wind_from_direction": 140,
          "wind_speed": 1.4,
          "wind_speed_of_gust": 5.7,
          "relative_humidity": 85,
          "air_pressure_at_mean_sea_level": 1009,
          "visibility_in_air": 1.9,
          "thunderstorm_probability": 0,
          "probability_of_frozen_precipitation": 0,
          "cloud_area_fraction": 7,
          "low_type_cloud_area_fraction": 6,
          "medium_type_cloud_area_fraction": 5,
          "high_type_cloud_area_fraction": 3,
          "cloud_base_altitude": 2370,
          "cloud_top_altitude": 5402,
          "mtpr": 0,
          "precipitation_amount_mean": 1,
          "precipitation_amount_min": 1.2,
          "precipitation_amount_max": 3.9,
          "precipitation_amount_median": 0,
          "probability_of_precipitation": 29,
          "precipitation_frozen_part": 0.94,
          "predominant_precipitation_type_at_surface": 5,
          "symbol_code": 4
        }
      },
      {
        "time": "2025-11-23T00:00:00Z",
        "intervalParametersStartTime": "2025-11-22T12:00:00Z",
        "data": {
          "air_temperature": -10.3,
          "wind_from_direction": 144,
          "wind_speed": 1.5,
          "wind_speed_of_gust": 5.8,
          "relative_humidity": 85,
          "air_pressure_at_mean_sea_level": 1008.2,
          "visibility_in_air": 1.5,
          "thunderstorm_probability": 0,
          "probability_of_frozen_precipitation": 0,
          "cloud_area_fraction": 8,
          "low_type_cloud_area_fraction": 6,
          "medium_type_cloud_area_fraction": 4,
          "high_type_cloud_area_fraction": 4,
          "cloud_base_altitude": 1942,
          "cloud_top_altitude": 5809,
          "mtpr": 0,
          "precipitation_amount_mean": 0.9,
          "precipitation_amount_min": 1,
          "precipitation_amount_max": 2.6,
          "precipitation_amount_median": 0,
          "probability_of_precipitation": 32,
          "precipitation_frozen_part": 0.94,
          "predominant_precipitation_type_at_surface": 5,
          "symbol_code": 4
        }
      },
      {
        "time": "2025-11-23T12:00:00Z",
        "intervalParametersStartTime": "2025-11-23T00:00:00Z",
        "data": {
          "air_temperature": -10.1,
          "wind_from_direction": 130,
          "wind_speed": 2.2,
          "wind_speed_of_gust": 6.7,
          "relative_humidity": 85,
          "air_pressure_at_mean_sea_level": 1007.6,
          "visibility_in_air": 2.5,
          "thunderstorm_probability": 0,
          "probability_of_frozen_precipitation": 0,
          "cloud_area_fraction": 8,
          "low_type_cloud_area_fraction": 6,
          "medium_type_cloud_area_fraction": 4,
          "high_type_cloud_area_fraction": 4,
          "cloud_base_altitude": 2238,
          "cloud_top_altitude": 5361,
          "mtpr": 0,
          "precipitation_amount_mean": 0.8,
          "precipitation_amount_min": 1.1,
          "precipitation_amount_max": 3.5,
          "precipitation_amount_median": 0,
          "probability_of_precipitation": 27,
          "precipitation_frozen_part": 1,
          "predominant_precipitation_type_at_surface": 5,
          "symbol_code": 4
        }
      },
      {
        "time": "2025-11-24T00:00:00Z",
        "intervalParametersStartTime": "2025-11-23T12:00:00Z",
        "data": {
          "air_temperature": -8.9,
          "wind_from_direction": 124,
          "wind_speed": 2.1,
          "wind_speed_of_gust": 6.7,
          "relative_humidity": 85,
          "air_pressure_at_mean_sea_level": 1006.2,
          "visibility_in_air": 1.6,
          "thunderstorm_probability": 0,
          "probability_of_frozen_precipitation": 0,
          "cloud_area_fraction": 8,
          "low_type_cloud_area_fraction": 6,
          "medium_type_cloud_area_fraction": 4,
          "high_type_cloud_area_fraction": 4,
          "cloud_base_altitude": 1944,
          "cloud_top_altitude": 5384,
          "mtpr": 0,
          "precipitation_amount_mean": 0.6,
          "precipitation_amount_min": 1.3,
          "precipitation_amount_max": 3.1,
          "precipitation_amount_median": 0,
          "probability_of_precipitation": 28,
          "precipitation_frozen_part": 0.94,
          "predominant_precipitation_type_at_surface": 5,
          "symbol_code": 4
        }
      },
      {
        "time": "2025-11-24T12:00:00Z",
        "intervalParametersStartTime": "2025-11-24T00:00:00Z",
        "data": {
          "air_temperature": -8.4,
          "wind_from_direction": 127,
          "wind_speed": 2.3,
          "wind_speed_of_gust": 6.6,
          "relative_humidity": 87,
          "air_pressure_at_mean_sea_level": 1006,
          "visibility_in_air": 2.5,
          "thunderstorm_probability": 0,
          "probability_of_frozen_precipitation": 0,
          "cloud_area_fraction": 8,
          "low_type_cloud_area_fraction": 7,
          "medium_type_cloud_area_fraction": 4,
          "high_type_cloud_area_fraction": 4,
          "cloud_base_altitude": 1614,
          "cloud_top_altitude": 5151,
          "mtpr": 0,
          "precipitation_amount_mean": 0.4,
          "precipitation_amount_min": 0.8,
          "precipitation_amount_max": 1.8,
          "precipitation_amount_median": 0,
          "probability_of_precipitation": 27,
          "precipitation_frozen_part": 0.94,
          "predominant_precipitation_type_at_surface": 5,
          "symbol_code": 4
        }
      },
      {
        "time": "2025-11-25T00:00:00Z",
        "intervalParametersStartTime": "2025-11-24T12:00:00Z",
        "data": {
          "air_temperature": -8.4,
          "wind_from_direction": 131,
          "wind_speed": 2.5,
          "wind_speed_of_gust": 6.6,
          "relative_humidity": 88,
          "air_pressure_at_mean_sea_level": 1004.9,
          "visibility_in_air": 1.3,
          "thunderstorm_probability": 0,
          "probability_of_frozen_precipitation": 0,
          "cloud_area_fraction": 8,
          "low_type_cloud_area_fraction": 7,
          "medium_type_cloud_area_fraction": 4,
          "high_type_cloud_area_fraction": 4,
          "cloud_base_altitude": 1686,
          "cloud_top_altitude": 5265,
          "mtpr": 0,
          "precipitation_amount_mean": 0.5,
          "precipitation_amount_min": 0.9,
          "precipitation_amount_max": 1.8,
          "precipitation_amount_median": 0,
          "probability_of_precipitation": 31,
          "precipitation_frozen_part": 0.94,
          "predominant_precipitation_type_at_surface": 5,
          "symbol_code": 4
        }
      },
      {
        "time": "2025-11-25T12:00:00Z",
        "intervalParametersStartTime": "2025-11-25T00:00:00Z",
        "data": {
          "air_temperature": -8.9,
          "wind_from_direction": 123,
          "wind_speed": 2.6,
          "wind_speed_of_gust": 6.7,
          "relative_humidity": 87,
          "air_pressure_at_mean_sea_level": 1004.1,
          "visibility_in_air": 2,
          "thunderstorm_probability": 0,
          "probability_of_frozen_precipitation": 0,
          "cloud_area_fraction": 8,
          "low_type_cloud_area_fraction": 7,
          "medium_type_cloud_area_fraction": 4,
          "high_type_cloud_area_fraction": 4,
          "cloud_base_altitude": 1688,
          "cloud_top_altitude": 5569,
          "mtpr": 0,
          "precipitation_amount_mean": 0.5,
          "precipitation_amount_min": 1,
          "precipitation_amount_max": 2.2,
          "precipitation_amount_median": 0,
          "probability_of_precipitation": 29,
          "precipitation_frozen_part": 0.94,
          "predominant_precipitation_type_at_surface": 5,
          "symbol_code": 4
        }
      }
    ]
  }